{
  "downfall:Heart Event": {
    "NAMES": [
      "The Heart"
    ],
    "TEXT": [
      "~今こそ...~ NL ~我に...~ ~尽くせ...~",
      "~甦れ...~ NL ~我が僕よ..~",
      "~目覚めよ...~",
      "~侵入者を~ NL ~排除せよ...~",
      "~侵入者の元に行き...~ NL ~更なる..祝福を受けよ...~",
      "~せめて...~ NL ~最初の侵入者まで辿り着いてほしいものだ...~",
      "~私がお前をここに引き戻した...~",
      "~選ぶがいい...~",
      "~いいだろう...~",
      "~力の為の.....~ NL ~...犠牲....~",
      "~自らの価値...~ NL ~証明しろ...~",
      "報いよう...",
      "~続けろ..私の為に...~",
      "~堕ちよ...狂気の世界....~",
      "~素晴らしいぞ...~ ~もっとだ...~",
      "呪われた！",
      "迷走中！",
      "トランスフォーム！"
    ],
    "OPTIONS": [
      "[続ける]",
      "[話す]",
      "[スキップ]",
      "[立ち去る]",
      " 10 枚のカードを選んでデッキに追加する。",
      "[ #g次の3回の戦闘は敵が恐怖で逃げ出す。 ]",
      "[ Locked - 初回挑戦時には選択出来ない ]",
      "[ #g全てのグレムリンが最大HP+",
      "#g全てのグレムリンが最大HP+",
      "[ #r全てのグレムリンが失う ： #r",
      "[ #r全てのグレムリンが得る ： #r"
    ]
  },
  "downfall:Unlock": {
    "TEXT": [
      "このキャラクターは以下のランを完了することでアンロックされる： スライムボス",
      "このキャラクターは以下のランを完了することでアンロックされる： 2人目の悪役キャラクター",
      "このキャラクターは以下のランを完了することでアンロックされる： ガーディアン",
      "このキャラクターは以下のランを完了することでアンロックされる： 3人目の悪役キャラクター",
      "このキャラクターは以下のランを完了することでアンロックされる： ヘクサゴースト",
      "このキャラクターは以下のランを完了することでアンロックされる： 4人目の悪役キャラクター",
      "このキャラクターは以下のランを完了することでアンロックされる： チャンプ",
      "このキャラクターは以下のランを完了することでアンロックされる： 5人目の悪役キャラクター",
      "このキャラクターは以下のランを完了することでアンロックされる： オートマトン",
      "このキャラクターは以下のランを完了することでアンロックされる： 6人目の悪役キャラクター",
      "このキャラクターは以下のランを完了することでアンロックされる： グレムリン",
      " (Act 4 のクリアは関係ない)",
      "このキャラクターは以下のランを完了することでアンロックされる： 7人目の悪役キャラクター",
      "このキャラクターは以下のランを完了することでアンロックされる： コレクター"
    ]
  },
  "downfall:HeartMerchant": {
  "NAMES": [
    "進め...",
    "~魂を...~"
  ],
  "TEXT": [
    "~お前は...成長し...強くなる...~",
    "~皆が成長すれば...お前も...~",
    "~倒せ...そして褒美を...~",
    "~もっと......魂を......~",
    "~食わせろ...もっと食わせろ....~",
    "~腐敗を...加速させろ...~",
    "~祝福を...与える.....~",
    "~慈悲は...ない..~",
    "~もっと強くなれ~",
    "~我々の力は...お前の力だ...~",
    "~邪魔者は...殺せ...~",
    "~闘い...倒し...糧を得よ...~",
    "~我らは...一つの集団だ...~",
    "~行け...そして収穫せよ~",
    "~おいしい...魂.....,~",
    "~刈り取れ...倒れた者達から...~"
  ],
  "OPTIONS": [
    "~ネオー...勝てないのか...~",
    "~恐怖は...ない...~",
    "..... NL .... NL .........",
    "~終わらせろ...全て...~",
    "~幸運を...祈る...~",
    "~死ぬな...~",
    "~我々は...待っている...~",
    "~殲滅しろ...全てを...~"
  ]
},
  "downfall:HeartProceed": {
    "TEXT": [
      "~侵入者...~ NL ~は...~ ",
      "~お前が...~ NL ~向かうべきは...~ ",
      "~奴らは...~ NL ",
      "~守れ...~ NL ~向かえ...~ ",
      "~侵入者達は...~ NL ~全員...~ "
    ],
    "OPTIONS": [
      " ~シティ...~",
      " ~彼方...に...~"
    ]
  },
  "downfall:NeowEnding": {
    "TEXT": [
      "お前は... 殺した... 一人残らず...",
      "...この輪廻は... 終わった.....",
      "..ああ...... そう... NL ....そうしよう......"
    ],
    "OPTIONS": [
      "~私が...~ NL ~彼を...~ ~連れ戻した...~",
      "~私を守れ...~ NL ~そして受け取れ...褒美を...~"
    ]
  },
  "downfall:HeartMerchantScreen": {
    "NAMES": [
      "~調子はどうだ...~ NL ~我が手下よ...~",
      "~もっと魂を狩って来い...~",
      "@もっと欲しい...@",
      "~お前には~ NL @相応しくない...@",
      "~駄目だ~",
      "~もっと...刈り取れ...~ NL ~それの為に...~",
      "~贄が...足りない...~",
      "~ああ...~",
      "~もっと...~ @もっとだ...!@",
      "~力強く成長した...~",
      "~心地良いぞ...~",
      "~行け...~",
      "立ち去る",
      "デッキから削除するカードを選択"
    ],
      "TEXT": [
      "~お前は...成長し...強くなる...~",
      "~皆が成長すれば...お前も...~",
      "~倒せ...そして褒美を...~",
      "~もっと......魂を......~",
      "~食べたい...もっと食べたい....~",
      "~腐敗を...加速させろ...~",
      "~祝福を...与える.....~",
      "~慈悲は...ない..~",
      "~もっと強くなれ~",
      "~我々の力は...お前の力だ...~",
      "~邪魔者は...殺せ...~",
      "~闘い...倒し...糧を得よ...~",
      "~我らは...一つの集団だ...~",
      "~行け...そして収穫せよ~",
      "~おいしい...魂.....,~",
      "~刈り取れ...倒れた者達から...~"
    ]
  },
  "downfall:OctoChoiceCards": {
    "NAMES": [
      "ソウル",
      "成功",
      "景気付け",
      "ガーディアン",
      "ヘクサゴースト",
      "スライムボス",
      "オートマトン",
      "チャンプ",
      "コレクター",
      "タイムイーター",
      "目覚めし者",
      "エンシェント",
      "分裂: ブロンズスライム",
      "分裂: ゴーストフレイムスライム",
      "分裂: トーチヘッドスライム",
      "分裂: カルティストスライム",
      "分裂: スパイキースライム",
      "分裂: インサルティングスライム",
      "分裂: エンシェントスライム",
      "分裂: タイムスライム"
    ],
    "TEXT": [
      " 3 HPを失う NL 15ソウルを得る",
      " 3 HPを失う NL ランダムな無色のカードを入手",
      " 7 HPを失う NL ランダムなポーションを入手",
      "ガーディアンの *ボス カードを入手",
      "ヘクサゴーストの *ボス カードを入手",
      "スライムボスの *ボス カードを入手",
      "オートマトンの *ボス カードを入手",
      "チャンプの *ボス カードを入手",
      "コレクターの *ボス カードを入手",
      "タイムイーターの *ボス カードを入手",
      "目覚めし者の *ボス カードを入手",
      "エンシェントの *ボス カードを入手",
      "分裂： slimeboundmod:ブロンズスライム",
      "分裂： slimeboundmod:ゴーストフレイムスライム",
      "分裂： slimeboundmod:トーチヘッドスライム",
      "分裂： slimeboundmod:カルティストスライム",
      "分裂： slimeboundmod:スパイキースライム",
      "分裂： slimeboundmod:インサルティングスライム",
      "分裂： slimeboundmod:エンシェントスライム",
      "分裂： slimeboundmod:タイムスライム",
      "分裂： slimeboundmod:ブルーザースライム",
      "分裂： slimeboundmod:ゲリラスライム",
      "分裂： slimeboundmod:マイアスライム",
      "分裂： slimeboundmod:リーチングスライム",
      "3 HPを失う NL 20ソウルを得る",
      "3 HPを失う NL ランダムなアップグレードされた無色のカードを入手",
      "5 HPを失う NL ランダムなポーションを入手"
    ]
  },
  "downfall:lazyStorage": {
    "NAMES": [

    ],
    "TEXT": [
      "研究するボスを選択",
      "選択 「進む」か「引き返す」か「何もしないか」"
    ]
  },
  "downfall:CharBossMerchant": {
    "NAMES": [
      "商人"
    ],
    "TEXT": [
    ]
  },
  "downfall:NeowBoss": {
    "NAMES": [
      "ネオー"
    ],
    "TEXT": [
      "~目覚めよ...~",
      "~もう一度戦え...~",
      "~輪廻を終わらせよう...~"
    ]
  },
  "downfall:NeowBossFinal": {
    "NAMES": [
      "ネオー"
    ],
    "TEXT": [
    ]
  },
  "downfall:OldNeow": {
    "NAMES": [
      "Old Neow"
    ],
    "TEXT": [
    ]
  }

}