{
  "hexamod:WanderingSpecter": {
    "NAME": "游荡幽灵",
    "DESCRIPTIONS": [
      "这片地区似乎是尖塔的 #p墓地 。正当你小心翼翼地穿过时，一个奇怪的微弱 ~鬼影~ 使你停下脚步。 它伸出双手，似乎在提供某种 #r交易 。",
      "真是一笔划算的买卖。你立即 @倒下@ 了。 NL NL 之后你在塔内的一片空地上醒来，脚边放着一个 #g宝物 。 你离开时，感到被， ~怪异~ ~的目光~ 注视着……",
      "你摇了摇头， #b鬼影 吃力地看了你最后一眼，继续它 ~无休止的~ ~漫步。~ 你也继续了你的旅程。 ",
	  "你接过一个 #y金光闪闪 的盒子，打开时感觉有一股 #p黑暗的力量 从身边传过。向其中定睛一看，是一件趁手的武器！",
      "你接过一个 @跃动@ 着的盒子，感觉似乎要 @流入@ 你的手臂一般。一股 #p邪恶 的气息在身体中涌动，但是你觉得你变强了……",
      "从神像上扣下遗物时， #p黑暗的力量 充满了整个房间。幽灵再一次对你说话，一种你从未听过的话语出现在你的脑海里。 NL NL #p“一个明智的选择。再来笔交易怎么样，我的朋友？这里的东西随便拿走……”",
	  "你发现这个 #p幽灵 卖的东西有点贵了。你得解决他。太巧了！在墙上！有个 #b蓝蜡烛！ NL NL 你从墙上抢走蜡烛并 #r开始咏唱 ，接着把它丢向了那个鬼魂， #y幽灵 立刻化为了一团 #b诡异的烟雾 。 NL NL 它再也不能跟你做交易了。",
      "你发现这个 #p幽灵 卖的东西有点贵了。你得解决他。太巧了！在墙上！有 #b蓝蜡烛！你身上带着 #b蓝蜡烛！ 你掏出蜡烛并 #r开始咏唱 ，接着把它丢向了那个鬼魂， #y幽灵 立刻化为了一团 #b诡异的烟雾 。 NL NL 它再也不能跟你做交易了。"
    ],
    "OPTIONS": [
	  "[左手] #g获得巫毒娃娃或黑石护符。 #r被诅咒2次-闹鬼。",
	  "[再买点]",
	  "[右手] #g获得诅咒钥匙或召唤铃铛。 #r被诅咒2次-随机。",
      "[赶跑] #g获得蓝蜡烛。 #r失去5点生命。",
      "[赶跑] 离开。",
	  "[换取力量] #g获得一张随机稀有牌。 #r被诅咒-随机。",
	  "[换取生命] #g获得5点最大生命。 #r被诅咒-随机。",
      "[换取灵魂] #g获得100灵魂。 #r被诅咒-随机。",
      "[锁定] 交易完成。",
	  "[离开]"
    ]
  },
  "hexamod:SealChamber": {
    "NAME": "容器议厅",
    "DESCRIPTIONS": [
      "一个恐怖的建筑在你面前。大多数人都不敢接近它，但你知道它的目的，也知道它有很大的用处。 NL 你进入房间准备献祭……",
      "献上了你灵魂的一部分，获得了容器 - 在通往终极力量的道路上又前进了一步。",
      "权衡你的选择，你决定不在密封室献祭。你自己会在旅途中得到想要的一切。",
	  "这些容器应该在以后能用上。"
    ],
    "OPTIONS": [
      "[献上] #r失去 ",
      " 生命。 #g获得第一容器。",
      " 金币。 #g获得第二容器。",
      " 。 #g获得第三容器。",
      " 。 #g获得第四容器。",
      "[锁定] 需要更多的金币。",
      "[锁定] 需要一张普通牌。",
      "[锁定] 需要一瓶药水。",
      "[离开]",
	  "[锁定] 需要贡品"
    ]
  },
  "hexamod:HexaFalling": {
    "NAME": "六火坠落",
    "DESCRIPTIONS": [
      "你，突然不受引力束缚，平稳地 ~飘落~ 在地。",
      "内心毫无波动……"
    ],
    "OPTIONS": [
      "[漂浮] #r什么都不失去……",
      "[离开]"
    ]
  },
  "hexamod:CouncilOfGhosts": {
    "NAME": "幽灵议会",
    "DESCRIPTIONS": [
      "在你向下深入时，突然四周的墙壁和地面开始冒出 #p~浓重的黑烟~ ，逐渐聚成了三个戴着面具的形状，它们交头接耳地说起话来。 NL NL ~“这个已经 #r~毁了...”~ NL “我们知道你的困境，被 #p诅咒 者... 你想不想了解一下我们的 #y~秘密~ 呢？”",
      "#y“好极了！” NL 那个幽灵鬼影的话音刚落，你就看见它本已硕大的嘴张开得越来越大，从中涌出更多 #p~浓重的黑烟~ 笼罩了整个房间。你什么也看不见，也无法呼吸……",
      "房间里依旧笼罩着 #p~浓重的黑烟~ ，你的躯体枯萎凋零，但你的精神愈发 #p炽热明亮 。 NL 你理解了实界与虚界的连接方式，那是你未曾设想过的。",
      "在黑暗之中，你的视野明如白昼。 鬼影们教会了你掌控形态的方式，让你能够在两种形态间变换自如。",
      "“祝你好运，被 #p诅咒 者。” NL ~“我们会留在这里帮助其他人...”~ NL #r@“哈哈@ #r@哈哈哈哈！”@ NL NL 你不太明白幽灵议会消失前的为什么要笑， 但你还是很感激他们提供的知识。",
      "“真令人失望……” NL ~“你永远别想逃出这个地方...”~ NL #r@“哈哈@ #r@哈哈哈哈！”@ NL NL 那些幽影消散了，只留下这令人不安的大笑声在你耳中回荡。"
      ],
    "OPTIONS": [
      "[接受] #r失去 #r",
      " #r最大生命。解锁研究和学习选项。",
      "[研究] #r失去所有的打击。 #g获得3张议会裁决。",
      "[学习] #r失去所有的防御。 #g获得3张灵体。",
      "[完成]",
      "[离开]",
      "[锁定] 还不能离开。"
    ]
  },
    "hexamod:BackToBasics": {
    "NAME": "",
    "DESCRIPTIONS": [
      "精神是剑，经验是磨刀石。"
    ],
    "OPTIONS": [
      "[渴望] #g将打击和防御加上虚无",
      "[锁定] 需要打击和防御"
    ]
  }
}