{
  "awakened:Thunderbolt": {
    "NAME": "Thunderbolt",
    "DESCRIPTION": "Deal !D! damage. NL Exhaust."
  },
  "awakened:BurningStudy": {
    "NAME": "Burning Study",
    "DESCRIPTION": "Exhaust 1 card. NL Gain !M! Strength. NL Exhaust."
  },
  "awakened:Cryostasis": {
    "NAME": "Cryostasis",
    "DESCRIPTION": "Gain !B! Block. NL Gain !M! Artifact. NL Exhaust."
  },
  "awakened:Darkleech": {
    "NAME": "Darkleech",
    "DESCRIPTION": "ALL enemies lose !M! HP. NL Draw !awakened:m2! card. NL Exhaust.",
    "UPGRADE_DESCRIPTION": "ALL enemies lose !M! HP. NL Draw !awakened:m2! cards. NL Exhaust."
  }
}
