{
	"hermit:Momento": {
		"NAME": "Старый кулон",
		"FLAVOR": "Внутри выцветшая фотография.",
		"DESCRIPTIONS": [
			"Добавляет в руку #rНапоминание, в начале боя."
		]
	},
	"hermit:RyeStalk": {
		"NAME": "Стебель пшеницы",
		"FLAVOR": "Всё ещё свежий, несмотря на то, что его так долго пережёвывали.",
		"DESCRIPTIONS": [
			"ВСЕ враги теряют ОЗ, равное их #yТравме, в конце вашего хода."
		]
	},
	"hermit:BartenderGlass": {
		"NAME": "Рюмка",
		"FLAVOR": "Любая, налитая в этот стакан, жидкость превращается во что-то иное.",
		"DESCRIPTIONS": [
			"Даёт случ. зелье при первых #b2 зельях, использованных в каждом бою. Вы можете использовать не более #b2 зелий в каждом бою.",
			"Вы больше не можете использовать зелья в этом бою."
		]
	},
	"hermit:Horseshoe": {
		"NAME": "Подкова",
		"FLAVOR": "Символ удачи. Кому-то он не помог.",
		"DESCRIPTIONS": [
			"Вы получаете на #b1 меньше #yСлабости, #yУязвимости и #yХрупкости."
		]
	},
	"hermit:Spyglass": {
		"NAME": "Подзорная труба",
		"FLAVOR": "Принадлежит Кестину Хайфину.",
		"DESCRIPTIONS": [
			"Даёт [E] в начале вашего хода, если у вас была #yКонцентрация в конце предыдущего хода."
		]
	},
	"hermit:RedScarf": {
		"NAME": "Красный шарф",
		"FLAVOR": "Меховой и тёплый.",
		"DESCRIPTIONS": [
			"Даёт #b2 #yЗащиты, когда вы накладываете отриц. эффект на врага."
		]
	},
	"hermit:DentedPlate": {
		"NAME": "Смятая пластина",
		"FLAVOR": "В ней всё ещё осталось несколько пуль.",
		"DESCRIPTIONS": [
			"Вы получаете [E] и берёте карту в начале вашего хода, при потере #b50% ОЗ."
		]
	},
	"hermit:PetGhost": {
		"NAME": "Призрак в банке",
		"FLAVOR": "Бедняга.",
		"DESCRIPTIONS": [
			"Вместо того, чтобы умереть, вы выживаете с #b1 ОЗ (1 раз за бой)."
		]
	},
	"hermit:CharredGlove": {
		"NAME": "Обгоревшая перчатка",
		"FLAVOR": "Куски ткани на этой перчатки до сих пор горят неземным пламенем.",
		"DESCRIPTIONS": [
			"Ваша след. #yАтака наносит на #b3 урона больше, когда вы берёте #rПроклятие."
		]
	},
	"hermit:ClaspedLocket": {
		"NAME": "Закрытый кулон",
		"FLAVOR": "Он больше никогда не откроется.",
		"DESCRIPTIONS": [
			"Заменяет #g«Старый #gкулон». При получении, даёт #b2 #rТравмы. Когда вы впервые за ход берёте Проклятие, оно #yСжигается и вы берёте 2 карты.",
			"Больше никогда..."
		]
	},
	"hermit:StraightRazor": {
		"NAME": "Ручная бритва",
		"FLAVOR": "Для более чистого бритья...",
		"DESCRIPTIONS": [
			"Восполняет #b15 ОЗ, когда вы убираете карту из колоды."
		]
	},
	"hermit:BrassTacks": {
		"NAME": "Латунные гвозди",
		"FLAVOR": "Блеск на этих гвоздях, кажется, никогда не исчезнет.",
		"DESCRIPTIONS": [
			"Вы начинаете каждый бой с #b2 #yМеталлизации."
    ]
  },
  "hermit:BlackPowder": {
		"NAME": "Чёрный порох",
		"FLAVOR": "Обращаться с осторожностью.",
		"DESCRIPTIONS": [
			"Наносит #b2 урона ВСЕМ врагам, за каждый активированный эффект #yВ #yяблочко, в конце вашего хода."
    ]
  },
  "hermit:BloodyTooth": {
		"NAME": "Сломанный зуб",
		"FLAVOR": "Выглядит слишком большим, чтобы выпасть из человеческой челюсти...",
		"DESCRIPTIONS": [
			"Даёт #b1 #yСилы за каждую победу над Элитным врагом, в начале боя, до конца текущего Акта."
    ]
  }
}